{
  "lottery_name": "SUVARNA KERALAM",
  "draw_number": "SK-17",
  "draw_date": "2025-08-29",
  "venue": "",
  "prizes": {
    "1st_prize": {
      "amount": 10000000,
      "label": "1st Prize",
      "winners": [
        "RE 302032(ERNAKULAM)"
      ]
    },
    "consolation_prize": {
      "amount": 5000,
      "label": "Consolation Prize",
      "winners": [
        "RA 302032",
        "RB 302032",
        "RC 302032",
        "RD 302032",
        "RF 302032",
        "RG 302032",
        "RH 302032",
        "RJ 302032",
        "RK 302032",
        "RL 302032",
        "RM 302032"
      ]
    },
    "2nd_prize": {
      "amount": 3000000,
      "label": "2nd Prize",
      "winners": [
        "RF 739176\r\n(MANANTHAVADY)"
      ]
    },
    "3rd_prize": {
      "amount": 500000,
      "label": "3rd Prize",
      "winners": [
        "RC 319936"
      ]
    },
    "4th_prize": {
      "amount": 5000,
      "label": "4th Prize",
      "winners": [
        "0515",
        "0603",
        "1385",
        "1655",
        "1749",
        "2669",
        "2837",
        "3579",
        "4761",
        "6196",
        "6552",
        "6628",
        "6668",
        "6766",
        "6851",
        "7175",
        "7523",
        "8044",
        "9096",
        "9248"
      ]
    },
    "5th_prize": {
      "amount": 2000,
      "label": "5th Prize",
      "winners": [
        "0523",
        "7182",
        "7561",
        "7632",
        "7649",
        "9646"
      ]
    },
    "6th_prize": {
      "amount": 1000,
      "label": "6th Prize",
      "winners": [
        "8111",
        "8267",
        "8021",
        "1222",
        "3065",
        "8236",
        "5926",
        "9621",
        "6404",
        "0247",
        "0389",
        "1686",
        "5880",
        "3794",
        "3945",
        "8946",
        "4608",
        "..."
      ]
    },
    "7th_prize": {
      "amount": 500,
      "label": "7th Prize",
      "winners": [
        "**"
      ]
    },
    "8th_prize": {
      "amount": 200,
      "label": "8th Prize",
      "winners": [
        "**"
      ]
    },
    "9th_prize": {
      "amount": 100,
      "label": "9th Prize",
      "winners": [
        "**"
      ]
    }
  },
  "downloadLink": ""
}