{
  "lottery_name": "SUVARNA KERALAM",
  "draw_number": "36",
  "draw_date": "2026-01-16",
  "venue": "GORKY BHAVAN NEAR BAKERY JUNCTION THIRUVANANTHAPURAM",
  "prizes": {
    "1st_prize": {
      "amount": 10000000,
      "label": "1st Prize",
      "winners": [
        "RV 285002"
      ]
    },
    "consolation_prize": {
      "amount": 5000,
      "label": "Consolation Prize",
      "winners": []
    },
    "2nd_prize": {
      "amount": 3000000,
      "label": "2nd Prize",
      "winners": [
        "RR 820833"
      ]
    },
    "3rd_prize": {
      "amount": 500000,
      "label": "3rd Prize",
      "winners": [
        "RU 850302"
      ]
    },
    "4th_prize": {
      "amount": 5000,
      "label": "4th Prize",
      "winners": [
        "0050",
        "1521",
        "2198",
        "3130",
        "3746",
        "4081",
        "4352",
        "4458",
        "4631",
        "5325",
        "5662",
        "6482",
        "6510",
        "7838",
        "8256",
        "8643",
        "9006",
        "9076",
        "9482"
      ]
    },
    "5th_prize": {
      "amount": 2000,
      "label": "5th Prize",
      "winners": [
        "0695",
        "3197",
        "3307",
        "4054",
        "5403",
        "9752"
      ]
    },
    "6th_prize": {
      "amount": 1000,
      "label": "6th Prize",
      "winners": []
    },
    "7th_prize": {
      "amount": 500,
      "label": "7th Prize",
      "winners": []
    },
    "8th_prize": {
      "amount": 200,
      "label": "8th Prize",
      "winners": []
    },
    "9th_prize": {
      "amount": 100,
      "label": "9th Prize",
      "winners": []
    }
  },
  "draw_code": "SK-36",
  "downloadLink": ""
}